colorvote/__init__.py
colorvote/__main__.py
colorvote/cli.py
colorvote/colorvote.py
colorvote/config.py
colorvote/database.py
colorvote/models.py
colorvote/rpc.py
colorvote-0.2.dist-info/LICENSE.txt
colorvote-0.2.dist-info/METADATA
colorvote-0.2.dist-info/WHEEL
colorvote-0.2.dist-info/top_level.txt
colorvote-0.2.dist-info/RECORD
