Metadata-Version: 2.1
Name: colorvote
Version: 0.2
Summary: A package for the colored coins voting protocol
Home-page: http://github.com/Ingimarsson/colorvote
Author: Brynjar Ingimarsson
Author-email: brynjar@ingimarsson.is
License: MIT
Platform: UNKNOWN
Requires-Python: >=3.6
Requires-Dist: requests
